odoo10_addon_purchase_procurement_analytic-10.0.1.0.2-py2.7-nspkg.pth
odoo/addons/purchase_procurement_analytic/README.rst
odoo/addons/purchase_procurement_analytic/__init__.py
odoo/addons/purchase_procurement_analytic/__manifest__.py
odoo/addons/purchase_procurement_analytic/i18n/ca.po
odoo/addons/purchase_procurement_analytic/i18n/cs_CZ.po
odoo/addons/purchase_procurement_analytic/i18n/de.po
odoo/addons/purchase_procurement_analytic/i18n/es.po
odoo/addons/purchase_procurement_analytic/i18n/es_AR.po
odoo/addons/purchase_procurement_analytic/i18n/es_MX.po
odoo/addons/purchase_procurement_analytic/i18n/fi.po
odoo/addons/purchase_procurement_analytic/i18n/fr.po
odoo/addons/purchase_procurement_analytic/i18n/hr.po
odoo/addons/purchase_procurement_analytic/i18n/hr_HR.po
odoo/addons/purchase_procurement_analytic/i18n/it.po
odoo/addons/purchase_procurement_analytic/i18n/pt.po
odoo/addons/purchase_procurement_analytic/i18n/pt_BR.po
odoo/addons/purchase_procurement_analytic/i18n/pt_PT.po
odoo/addons/purchase_procurement_analytic/i18n/purchase_procurement_analytic.pot
odoo/addons/purchase_procurement_analytic/i18n/sl.po
odoo/addons/purchase_procurement_analytic/i18n/tr.po
odoo/addons/purchase_procurement_analytic/i18n/tr_TR.po
odoo/addons/purchase_procurement_analytic/i18n/zh_CN.po
odoo/addons/purchase_procurement_analytic/models/__init__.py
odoo/addons/purchase_procurement_analytic/models/procurement.py
odoo/addons/purchase_procurement_analytic/models/stock.py
odoo/addons/purchase_procurement_analytic/static/description/icon.png
odoo/addons/purchase_procurement_analytic/tests/__init__.py
odoo/addons/purchase_procurement_analytic/tests/test_purchase_procurement_analytic.py
odoo10_addon_purchase_procurement_analytic-10.0.1.0.2.dist-info/DESCRIPTION.rst
odoo10_addon_purchase_procurement_analytic-10.0.1.0.2.dist-info/METADATA
odoo10_addon_purchase_procurement_analytic-10.0.1.0.2.dist-info/RECORD
odoo10_addon_purchase_procurement_analytic-10.0.1.0.2.dist-info/WHEEL
odoo10_addon_purchase_procurement_analytic-10.0.1.0.2.dist-info/metadata.json
odoo10_addon_purchase_procurement_analytic-10.0.1.0.2.dist-info/namespace_packages.txt
odoo10_addon_purchase_procurement_analytic-10.0.1.0.2.dist-info/top_level.txt
