Metadata-Version: 2.0
Name: odoo10-addon-purchase-procurement-analytic
Version: 10.0.1.0.2
Summary: This module sets analytic account in purchase order line from procurement analytic account
Home-page: http://www.tecnativa.com
Author: Tecnativa, Odoo Community Association (OCA)
Author-email: support@odoo-community.org
License: AGPL-3
Platform: UNKNOWN
Classifier: Programming Language :: Python
Classifier: Framework :: Odoo
Classifier: License :: OSI Approved :: GNU Affero General Public License v3
Requires-Python: ~=2.7
Requires-Dist: odoo (<10.1dev,>=10.0)
Requires-Dist: odoo10-addon-procurement-analytic
